<?xml version="1.0" encoding="utf-8" ?>
<Defs>


	<PawnKindDef ParentName="BANW_BasePawn">
		<defName>BANW_Reisa_A</defName>
		<label>-玲纱(魔法)-</label>
		<race>BANW_Reisa_A_race</race>
		<combatPower>100</combatPower>
		<isFighter>true</isFighter>
		<defaultFactionType>PlayerColony</defaultFactionType>
		<generateInitialNonFamilyRelations>false</generateInitialNonFamilyRelations>
		<humanPregnancyChance>0.0</humanPregnancyChance>
		<fixedGender>Female</fixedGender>
		<startingHediffs>
		<li>
			<def>BANW_LevelTrait</def>
			<severity>0.001</severity>
		</li>
        </startingHediffs>
		<abilities>
			<li>BAWN_Reisa_A_EX</li>
			<li>BAWN_Reisa_A_EXX</li>
		</abilities>
		<backstoryFiltersOverride>
			<li>
				<categories>
					<li>BANW_BackstorySany</li>
					<li>BANW_BackstoryReisa_A</li>
				</categories>
			</li>
		</backstoryFiltersOverride>
		<useFactionXenotypes>true</useFactionXenotypes>
		<weaponMoney>9999~9999</weaponMoney>
		<minGenerationAge>17</minGenerationAge>
		<maxGenerationAge>18</maxGenerationAge>
		<weaponTags>
         <li>BANC_Reisa_A</li>
        </weaponTags>
		<apparelRequired Inherit="False">
			<li>BANW_Body_Reisa_A</li>
		</apparelRequired>
		<forcedHair>Bald</forcedHair>

		<skills>
			<li>
				<skill>Shooting</skill>
				<range>15</range>
			</li>
			<li>
				<skill>Melee</skill>
				<range>8</range>
			</li>
			<li>
				<skill>Artistic</skill>
				<range>7~10</range>
			</li>
			<li>
				<skill>Construction</skill>
				<range>7</range>
			</li>
			<li>
				<skill>Crafting</skill>
				<range>8</range>
			</li>
			<li>
				<skill>Animals</skill>
				<range>10</range>
			</li>
			<li>
				<skill>Mining</skill>
				<range>7</range>
			</li>
			<li>
				<skill>Plants</skill>
				<range>8</range>
			</li>
			<li>
				<skill>Social</skill>
				<range>5</range>
			</li>
			<li>
				<skill>Intellectual</skill>
				<range>1</range>
			</li>
		</skills>
		<forcedTraits>
			<BAWC_TraitDef_Assistant>0</BAWC_TraitDef_Assistant>
			<BAWC_TraitDef_teshu>0</BAWC_TraitDef_teshu>
			<BAWC_TraitDef_Reisa_A_A>0</BAWC_TraitDef_Reisa_A_A>
		</forcedTraits>
	</PawnKindDef>
	<TraitDef>
        <defName>BAWC_TraitDef_Reisa_A_A</defName>
        <commonality>0</commonality>
        <degreeDatas>
            <li>
                <label>&lt;color=#990099&gt;火力是魔法！&lt;/color&gt;</label>
                <description>被动技能：自身生命值提升&lt;color=#DC143C&gt;26%&lt;/color&gt;</description>
                <marketValueFactorOffset>1</marketValueFactorOffset>
                <statOffsets> 

                </statOffsets>
				<statFactors>
				</statFactors>
            </li>
        </degreeDatas>
    </TraitDef>
</Defs>
