[
    {
        "CurrencyDefName": "BANW_Airy_race_Proplevel",
        "CurrencyAmount": 1,
        "CurrencyImage": "Prop/Proplevel/Airy",
        "ProductAmount": 5,
        "ProductImage": "Prop/Proplevel/Kami",
        "ProductDefName": "Kami_Proplevel",
        "ProductName": "爱莉/神明精髓",
        "ProductDescription": "一种神秘的文字，蕴含着未知的力量。似乎只能用于某些特殊的用途",
        "ProductQuality": "low"
    },
    {
        "CurrencyDefName": "BANW_Hanae_race_Proplevel",
        "CurrencyAmount": 1,
        "CurrencyImage": "Prop/Proplevel/Hanae",
        "ProductAmount": 5,
        "ProductImage": "Prop/Proplevel/Kami",
        "ProductDefName": "Kami_Proplevel",
        "ProductName": "花江/神明精髓",
        "ProductDescription": "一种神秘的文字，蕴含着未知的力量。似乎只能用于某些特殊的用途",
        "ProductQuality": "low"
    },
     {
        "CurrencyDefName": "BANW_Serina_race_Proplevel",
        "CurrencyAmount": 1,
        "CurrencyImage": "Prop/Proplevel/Serina",
        "ProductAmount": 1,
        "ProductImage": "Prop/Proplevel/Kami",
        "ProductDefName": "Kami_Proplevel",
        "ProductName": "芹娜/神明精髓",
        "ProductDescription": "一种神秘的文字，蕴含着未知的力量。似乎只能用于某些特殊的用途",
        "ProductQuality": "low"
    },
     {
        "CurrencyDefName": "BANW_Mine_race_Proplevel",
        "CurrencyAmount": 1,
        "CurrencyImage": "Prop/Proplevel/Mine",
        "ProductAmount": 30,
        "ProductImage": "Prop/Proplevel/Kami",
        "ProductDefName": "Kami_Proplevel",
        "ProductName": "美祢/神明精髓",
        "ProductDescription": "一种神秘的文字，蕴含着未知的力量。似乎只能用于某些特殊的用途",
        "ProductQuality": "low"
    },
    {
        "CurrencyDefName": "BANW_Natsu_race_Proplevel",
        "CurrencyAmount": 1,
        "CurrencyImage": "Prop/Proplevel/Natsu",
        "ProductAmount": 30,
        "ProductImage": "Prop/Proplevel/Kami",
        "ProductDefName": "Kami_Proplevel",
        "ProductName": "夏/神明精髓",
        "ProductDescription": "一种神秘的文字，蕴含着未知的力量。似乎只能用于某些特殊的用途",
        "ProductQuality": "low"
    },
    {
        "CurrencyDefName": "BANW_Kazusa_race_Proplevel",
        "CurrencyAmount": 1,
        "CurrencyImage": "Prop/Proplevel/Kazusa",
        "ProductAmount": 30,
        "ProductImage": "Prop/Proplevel/Kami",
        "ProductDefName": "Kami_Proplevel",
        "ProductName": "和纱/神明精髓",
        "ProductDescription": "一种神秘的文字，蕴含着未知的力量。似乎只能用于某些特殊的用途",
        "ProductQuality": "low"
    },
     {
        "CurrencyDefName": "BANW_Yoshimi_race_Proplevel",
        "CurrencyAmount": 1,
        "CurrencyImage": "Prop/Proplevel/Yoshimi",
        "ProductAmount": 1,
        "ProductImage": "Prop/Proplevel/Kami",
        "ProductDefName": "Kami_Proplevel",
        "ProductName": "好美/神明精髓",
        "ProductDescription": "一种神秘的文字，蕴含着未知的力量。似乎只能用于某些特殊的用途",
        "ProductQuality": "low"
    },
    {
        "CurrencyDefName": "BANW_Hasumi_race_Proplevel",
        "CurrencyAmount": 1,
        "CurrencyImage": "Prop/Proplevel/Hasumi",
        "ProductAmount": 5,
        "ProductImage": "Prop/Proplevel/Kami",
        "ProductDefName": "Kami_Proplevel",
        "ProductName": "莲见/神明精髓",
        "ProductDescription": "一种神秘的文字，蕴含着未知的力量。似乎只能用于某些特殊的用途",
        "ProductQuality": "low"
    },
    {
        "CurrencyDefName": "BANW_Ichika_race_Proplevel",
        "CurrencyAmount": 1,
        "CurrencyImage": "Prop/Proplevel/Ichika",
        "ProductAmount": 30,
        "ProductImage": "Prop/Proplevel/Kami",
        "ProductDefName": "Kami_Proplevel",
        "ProductName": "一花/神明精髓",
        "ProductDescription": "一种神秘的文字，蕴含着未知的力量。似乎只能用于某些特殊的用途",
        "ProductQuality": "low"
    },
    {
        "CurrencyDefName": "BANW_Koharu_race_Proplevel",
        "CurrencyAmount": 1,
        "CurrencyImage": "Prop/Proplevel/Koharu",
        "ProductAmount": 30,
        "ProductImage": "Prop/Proplevel/Kami",
        "ProductDefName": "Kami_Proplevel",
        "ProductName": "小春/神明精髓",
        "ProductDescription": "一种神秘的文字，蕴含着未知的力量。似乎只能用于某些特殊的用途",
        "ProductQuality": "low"
    },
     {
        "CurrencyDefName": "BANW_Hanako_race_Proplevel",
        "CurrencyAmount": 1,
        "CurrencyImage": "Prop/Proplevel/Hanako",
        "ProductAmount": 5,
        "ProductImage": "Prop/Proplevel/Kami",
        "ProductDefName": "Kami_Proplevel",
        "ProductName": "花子/神明精髓",
        "ProductDescription": "一种神秘的文字，蕴含着未知的力量。似乎只能用于某些特殊的用途",
        "ProductQuality": "low"
    },
    {
        "CurrencyDefName": "BANW_Hifumi_race_Proplevel",
        "CurrencyAmount": 1,
        "CurrencyImage": "Prop/Proplevel/Hifumi",
        "ProductAmount": 30,
        "ProductImage": "Prop/Proplevel/Kami",
        "ProductDefName": "Kami_Proplevel",
        "ProductName": "日富美/神明精髓",
        "ProductDescription": "一种神秘的文字，蕴含着未知的力量。似乎只能用于某些特殊的用途",
        "ProductQuality": "low"
    },
    {
        "CurrencyDefName": "BANW_Azusa_race_Proplevel",
        "CurrencyAmount": 1,
        "CurrencyImage": "Prop/Proplevel/Azusa",
        "ProductAmount": 30,
        "ProductImage": "Prop/Proplevel/Kami",
        "ProductDefName": "Kami_Proplevel",
        "ProductName": "梓/神明精髓",
        "ProductDescription": "一种神秘的文字，蕴含着未知的力量。似乎只能用于某些特殊的用途",
        "ProductQuality": "low"
    },
    {
        "CurrencyDefName": "BANW_Mari_race_Proplevel",
        "CurrencyAmount": 1,
        "CurrencyImage": "Prop/Proplevel/Mari",
        "ProductAmount": 5,
        "ProductImage": "Prop/Proplevel/Kami",
        "ProductDefName": "Kami_Proplevel",
        "ProductName": "玛丽/神明精髓",
        "ProductDescription": "一种神秘的文字，蕴含着未知的力量。似乎只能用于某些特殊的用途",
        "ProductQuality": "low"
    },
    {
        "CurrencyDefName": "BANW_Sakurako_race_Proplevel",
        "CurrencyAmount": 1,
        "CurrencyImage": "Prop/Proplevel/Sakurako",
        "ProductAmount": 30,
        "ProductImage": "Prop/Proplevel/Kami",
        "ProductDefName": "Kami_Proplevel",
        "ProductName": "樱子/神明精髓",
        "ProductDescription": "一种神秘的文字，蕴含着未知的力量。似乎只能用于某些特殊的用途",
        "ProductQuality": "low"
    },
     {
        "CurrencyDefName": "BANW_Hinata_race_Proplevel",
        "CurrencyAmount": 1,
        "CurrencyImage": "Prop/Proplevel/Hinata",
        "ProductAmount": 30,
        "ProductImage": "Prop/Proplevel/Kami",
        "ProductDefName": "Kami_Proplevel",
        "ProductName": "日向/神明精髓",
        "ProductDescription": "一种神秘的文字，蕴含着未知的力量。似乎只能用于某些特殊的用途",
        "ProductQuality": "low"
    },
    {
        "CurrencyDefName": "BANW_Mashiro_race_Proplevel",
        "CurrencyAmount": 1,
        "CurrencyImage": "Prop/Proplevel/Mashiro",
        "ProductAmount": 30,
        "ProductImage": "Prop/Proplevel/Kami",
        "ProductDefName": "Kami_Proplevel",
        "ProductName": "真白/神明精髓",
        "ProductDescription": "一种神秘的文字，蕴含着未知的力量。似乎只能用于某些特殊的用途",
        "ProductQuality": "low"
    },
    {
        "CurrencyDefName": "BANW_Mika_race_Proplevel",
        "CurrencyAmount": 1,
        "CurrencyImage": "Prop/Proplevel/Mika",
        "ProductAmount": 30,
        "ProductImage": "Prop/Proplevel/Kami",
        "ProductDefName": "Kami_Proplevel",
        "ProductName": "未花/神明精髓",
        "ProductDescription": "一种神秘的文字，蕴含着未知的力量。似乎只能用于某些特殊的用途",
        "ProductQuality": "low"
    },
     {
        "CurrencyDefName": "BANW_Nagisa_race_Proplevel",
        "CurrencyAmount": 1,
        "CurrencyImage": "Prop/Proplevel/Nagisa",
        "ProductAmount": 30,
        "ProductImage": "Prop/Proplevel/Kami",
        "ProductDefName": "Kami_Proplevel",
        "ProductName": "渚/神明精髓",
        "ProductDescription": "一种神秘的文字，蕴含着未知的力量。似乎只能用于某些特殊的用途",
        "ProductQuality": "low"
    },
    {
        "CurrencyDefName": "BANW_Reisa_race_Proplevel",
        "CurrencyAmount": 1,
        "CurrencyImage": "Prop/Proplevel/Reisa",
        "ProductAmount": 30,
        "ProductImage": "Prop/Proplevel/Kami",
        "ProductDefName": "Kami_Proplevel",
        "ProductName": "玲纱/神明精髓",
        "ProductDescription": "一种神秘的文字，蕴含着未知的力量。似乎只能用于某些特殊的用途",
        "ProductQuality": "low"
    },
    {
        "CurrencyDefName": "BANW_Seia_race_Proplevel",
        "CurrencyAmount": 1,
        "CurrencyImage": "Prop/Proplevel/Seia",
        "ProductAmount": 30,
        "ProductImage": "Prop/Proplevel/Kami",
        "ProductDefName": "Kami_Proplevel",
        "ProductName": "圣娅/神明精髓",
        "ProductDescription": "一种神秘的文字，蕴含着未知的力量。似乎只能用于某些特殊的用途",
        "ProductQuality": "low"
    },
    {
        "CurrencyDefName": "BANW_Shimiko_race_Proplevel",
        "CurrencyAmount": 1,
        "CurrencyImage": "Prop/Proplevel/Shimiko",
        "ProductAmount": 1,
        "ProductImage": "Prop/Proplevel/Kami",
        "ProductDefName": "Kami_Proplevel",
        "ProductName": "志美子/神明精髓",
        "ProductDescription": "一种神秘的文字，蕴含着未知的力量。似乎只能用于某些特殊的用途",
        "ProductQuality": "low"
    },
    {
        "CurrencyDefName": "BANW_Suzumi_race_Proplevel",
        "CurrencyAmount": 1,
        "CurrencyImage": "Prop/Proplevel/Suzumi",
        "ProductAmount": 1,
        "ProductImage": "Prop/Proplevel/Kami",
        "ProductDefName": "Kami_Proplevel",
        "ProductName": "铃美/神明精髓",
        "ProductDescription": "一种神秘的文字，蕴含着未知的力量。似乎只能用于某些特殊的用途",
        "ProductQuality": "low"
    },
    {
        "CurrencyDefName": "BANW_Turugi_race_Proplevel",
        "CurrencyAmount": 1,
        "CurrencyImage": "Prop/Proplevel/Turugi",
        "ProductAmount": 30,
        "ProductImage": "Prop/Proplevel/Kami",
        "ProductDefName": "Kami_Proplevel",
        "ProductName": "鹤城/神明精髓",
        "ProductDescription": "一种神秘的文字，蕴含着未知的力量。似乎只能用于某些特殊的用途",
        "ProductQuality": "low"
    } 
] 